fds/__init__.py
fds/sdk/__init__.py
fds/sdk/PortfolioReportingBatcher/__init__.py
fds/sdk/PortfolioReportingBatcher/api_client.py
fds/sdk/PortfolioReportingBatcher/configuration.py
fds/sdk/PortfolioReportingBatcher/exceptions.py
fds/sdk/PortfolioReportingBatcher/model_utils.py
fds/sdk/PortfolioReportingBatcher/rest.py
fds/sdk/PortfolioReportingBatcher/api/__init__.py
fds/sdk/PortfolioReportingBatcher/api/jobs_api.py
fds/sdk/PortfolioReportingBatcher/api/runs_api.py
fds/sdk/PortfolioReportingBatcher/apis/__init__.py
fds/sdk/PortfolioReportingBatcher/model/__init__.py
fds/sdk/PortfolioReportingBatcher/model/accounts_for_job.py
fds/sdk/PortfolioReportingBatcher/model/accounts_for_job_add_prop.py
fds/sdk/PortfolioReportingBatcher/model/calendar.py
fds/sdk/PortfolioReportingBatcher/model/client_error_response.py
fds/sdk/PortfolioReportingBatcher/model/documents_for_job.py
fds/sdk/PortfolioReportingBatcher/model/error.py
fds/sdk/PortfolioReportingBatcher/model/error_source.py
fds/sdk/PortfolioReportingBatcher/model/frequency.py
fds/sdk/PortfolioReportingBatcher/model/id_status.py
fds/sdk/PortfolioReportingBatcher/model/id_status_data.py
fds/sdk/PortfolioReportingBatcher/model/job_details_response.py
fds/sdk/PortfolioReportingBatcher/model/job_details_response_data.py
fds/sdk/PortfolioReportingBatcher/model/job_list_response.py
fds/sdk/PortfolioReportingBatcher/model/job_list_response_meta.py
fds/sdk/PortfolioReportingBatcher/model/job_list_response_meta_pagination.py
fds/sdk/PortfolioReportingBatcher/model/job_list_response_root.py
fds/sdk/PortfolioReportingBatcher/model/job_overrides.py
fds/sdk/PortfolioReportingBatcher/model/job_overrides_combinations_root.py
fds/sdk/PortfolioReportingBatcher/model/job_overrides_combinations_root_date_range.py
fds/sdk/PortfolioReportingBatcher/model/job_types.py
fds/sdk/PortfolioReportingBatcher/model/prb_status.py
fds/sdk/PortfolioReportingBatcher/model/runs_for_job.py
fds/sdk/PortfolioReportingBatcher/model/start_job.py
fds_sdk_portfolioreportingbatcher-2.0.0.dist-info/licenses/LICENSE
fds_sdk_portfolioreportingbatcher-2.0.0.dist-info/METADATA
fds_sdk_portfolioreportingbatcher-2.0.0.dist-info/WHEEL
fds_sdk_portfolioreportingbatcher-2.0.0.dist-info/top_level.txt
fds_sdk_portfolioreportingbatcher-2.0.0.dist-info/RECORD
